.gitignore
CHANGES.txt
README.rst
bootstrap.py
buildout.cfg
screenshot.png
setup.py
collective/__init__.py
collective.pluggablelogin.egg-info/PKG-INFO
collective.pluggablelogin.egg-info/SOURCES.txt
collective.pluggablelogin.egg-info/dependency_links.txt
collective.pluggablelogin.egg-info/entry_points.txt
collective.pluggablelogin.egg-info/namespace_packages.txt
collective.pluggablelogin.egg-info/not-zip-safe
collective.pluggablelogin.egg-info/requires.txt
collective.pluggablelogin.egg-info/top_level.txt
collective/pluggablelogin/__init__.py
collective/pluggablelogin/configure.zcml
collective/pluggablelogin/interfaces.py
collective/pluggablelogin/manage_portlets.pt
collective/pluggablelogin/register_portlet.pt
collective/pluggablelogin/register_portlet.py
collective/pluggablelogin/renderer.pt
collective/pluggablelogin/renderer.py
collective/pluggablelogin/testing.py
collective/pluggablelogin/profiles/default/metadata.xml
collective/pluggablelogin/profiles/default/portlets.xml
collective/pluggablelogin/profiles/default/skins.xml
collective/pluggablelogin/skins/pluggable_login/logged_out.cpt
collective/pluggablelogin/skins/pluggable_login/logged_out.cpt.metadata
collective/pluggablelogin/skins/pluggable_login/login_form.cpt
collective/pluggablelogin/skins/pluggable_login/login_form.cpt.metadata
collective/pluggablelogin/tests/__init__.py
collective/pluggablelogin/tests/test_login.py
docs/LICENSE.GPL
docs/LICENSE.txt