Metadata-Version: 1.1
Name: collective.pluggablelogin
Version: 1.2
Summary: Turns the login form into a portlet manager for easier customization
Home-page: http://github.com/collective/collective.pluggablelogin
Author: David Glick, Groundwire
Author-email: dglick@gmail.com
License: GPL
Platform: UNKNOWN
Classifier: Framework :: Plone
Classifier: Programming Language :: Python
Classifier: Topic :: Software Development :: Libraries :: Python Modules
